LICENSE
MANIFEST.in
README.md
setup.py
django_restify_framework.egg-info/PKG-INFO
django_restify_framework.egg-info/SOURCES.txt
django_restify_framework.egg-info/dependency_links.txt
django_restify_framework.egg-info/not-zip-safe
django_restify_framework.egg-info/requires.txt
django_restify_framework.egg-info/top_level.txt
restify/__init__.py
restify/api.py
restify/apps.py
restify/middleware.py
restify/models.py
restify/remote.py
restify/serializers.py
restify/signals.py
restify/testing.py
restify/authentication/__init__.py
restify/authentication/api.py
restify/authentication/base.py
restify/authentication/session.py
restify/authorization/__init__.py
restify/authorization/base.py
restify/authorization/django.py
restify/http/__init__.py
restify/http/response.py
restify/http/status.py
restify/migrations/0001_initial.py
restify/migrations/__init__.py
restify/resource/__init__.py
restify/resource/base.py
restify/resource/model.py
restify/task/__init__.py
restify/task/resource.py
restify/task/client/__init__.py
restify/task/client/auth.py
tests/__init__.py
tests/models.py
tests/settings.py
tests/test_api.py
tests/test_authentication.py
tests/test_authorization.py
tests/test_middleware.py
tests/test_response.py
tests/urls.py
tests/resources/__init__.py
tests/resources/test_base.py
tests/resources/test_model.py
tests/serializers/__init__.py
tests/serializers/test_base.py
tests/serializers/test_django.py
tests/serializers/test_model.py
tests/task/__init__.py
tests/task/test_resource.py
tests/task/test_task.py
tests/task/client/__init__.py
tests/task/client/test_auth.py
tests/task/client/test_client.py