Metadata-Version: 1.1
Name: django-restify-framework
Version: 1.0.0
Summary: Yet another django REST API
Home-page: http://lovasb.com
Author: Lovas Bence
Author-email: me@lovasb.com
License: MIT
Keywords: django,rest,api
Platform: UNKNOWN
Classifier: Programming Language :: Python
Classifier: Topic :: Software Development :: Libraries :: Python Modules
Classifier: Framework :: Django
Classifier: Environment :: Web Environment
Classifier: Operating System :: OS Independent
Classifier: Natural Language :: English
